genshin/__init__.py
genshin.py-0.0.1.dist-info/METADATA
genshin.py-0.0.1.dist-info/WHEEL
genshin.py-0.0.1.dist-info/top_level.txt
genshin.py-0.0.1.dist-info/RECORD
